kraven/__init__.py
kraven/__main__.py
kraven/constant.py
kraven/utils.py
kraven-0.1.0.dist-info/WHEEL
kraven-0.1.0.dist-info/METADATA
kraven-0.1.0.dist-info/RECORD
