Metadata-Version: 2.1
Name: kraven
Version: 0.1.0
Summary: 
Author: Jeremy Zabala
Author-email: jeremy.zbala@gmail.com
Requires-Python: >=3.7.2,<3.12
Classifier: Programming Language :: Python :: 3
Classifier: Programming Language :: Python :: 3.8
Classifier: Programming Language :: Python :: 3.9
Classifier: Programming Language :: Python :: 3.10
Classifier: Programming Language :: Python :: 3.11
Requires-Dist: furl (>=2.1.3,<3.0.0)
Requires-Dist: glom (>=23.1.1,<24.0.0)
Requires-Dist: gql[httpx,requests] (>=3.4.0,<4.0.0)
Requires-Dist: httpx (>=0.23.3,<0.24.0)
Requires-Dist: rich (>=13.2.0,<14.0.0)
Requires-Dist: toml (>=0.10.2,<0.11.0)
